cliqs/__init__.py
cliqs/__main__.py
cliqs/cliqs.py
cliqs/features_extraction.py
cliqs/utils.py
cliqs-1.0.0.dist-info/LICENSE
cliqs-1.0.0.dist-info/METADATA
cliqs-1.0.0.dist-info/WHEEL
cliqs-1.0.0.dist-info/entry_points.txt
cliqs-1.0.0.dist-info/top_level.txt
cliqs-1.0.0.dist-info/RECORD
