Metadata-Version: 2.1
Name: cliqs
Version: 1.0.0
Summary: Module provides implementation of multilingual crisis social media summarization model.
Author-email: Fedor Vitiugin <fedor.vitiugin@upf.edu>
License: MIT License
Project-URL: Homepage, https://github.com/vitiugin/cliqs
Keywords: text summarization,text classification,multilingual
Classifier: License :: OSI Approved :: MIT License
Classifier: Programming Language :: Python
Classifier: Programming Language :: Python :: 3
Requires-Python: >=3.8.0
License-File: LICENSE
Requires-Dist: absl-py (>=1.4.0)
Requires-Dist: beautifulsoup4 (>=4.12.0)
Requires-Dist: emoji (>=2.2.0)
Requires-Dist: huggingface-hub (>=0.13.3)
Requires-Dist: keras (>=2.11.0)
Requires-Dist: laserembeddings (>=1.1.2)
Requires-Dist: nltk (>=3.8.1)
Requires-Dist: numpy (>=1.24.2)
Requires-Dist: pandas (>=1.5.3)
Requires-Dist: scikit-learn (>=1.2.2)
Requires-Dist: scipy (>=1.10.1)
Requires-Dist: sklearn (>=0.0.post1)
Requires-Dist: spacy (>=3.5.1)
Requires-Dist: spacy-legacy (>=3.0.12)
Requires-Dist: spacy-loggers (>=1.0.4)
Requires-Dist: stanza (>=1.5.0)
Requires-Dist: subword-nmt (>=0.3.8)
Requires-Dist: SudachiDict-core (>=20230110)
Requires-Dist: SudachiPy (>=0.6.7)
Requires-Dist: sympy (>=1.11.1)
Requires-Dist: tensorboard (>=2.11.2)
Requires-Dist: tensorboard-data-server (>=0.6.1)
Requires-Dist: tensorboard-plugin-wit (>=1.8.1)
Requires-Dist: tensorflow (>=2.11.1)
Requires-Dist: tensorflow-estimator (>=2.11.0)
Requires-Dist: tensorflow-io-gcs-filesystem (>=0.31.0)
Requires-Dist: tokenizers (>=0.13.2)
Requires-Dist: torch (>=1.13.1)
Requires-Dist: tqdm (>=4.65.0)
Requires-Dist: transformers (>=4.27.2)
Requires-Dist: transliterate (>=1.10.2)
Requires-Dist: urllib3 (>=1.26.15)
Requires-Dist: wikipedia (>=1.4.0)
